{
    "number_of_nodes": 117.0,
    "number_of_edges": 117.0,
    "cascade_size": 116.0,
    "tree_depth": 5.0,
    "in_degree_distribution": [
        0,
        1,
        1,
        1,
        1,
        1,
        1,
        1,
        2,
        1,
        1,
        1,
        1,
        1,
        1,
        1,
        1,
        1,
        1,
        1,
        1,
        1,
        1,
        1,
        1,
        1,
        1,
        1,
        1,
        1,
        1,
        1,
        1,
        1,
        1,
        1,
        1,
        1,
        1,
        1,
        1,
        1,
        1,
        1,
        1,
        1,
        1,
        1,
        1,
        1,
        1,
        1,
        1,
        1,
        1,
        1,
        1,
        1,
        1,
        1,
        1,
        1,
        1,
        1,
        1,
        1,
        1,
        1,
        1,
        1,
        1,
        1,
        1,
        1,
        1,
        1,
        1,
        1,
        1,
        1,
        1,
        1,
        1,
        1,
        1,
        1,
        1,
        1,
        1,
        1,
        1,
        1,
        1,
        1,
        1,
        1,
        1,
        1,
        1,
        1,
        1,
        1,
        1,
        1,
        1,
        1,
        1,
        1,
        1,
        1,
        1,
        1,
        1,
        1,
        1,
        1,
        1
    ],
    "out_degree_distribution": [
        1,
        76,
        0,
        0,
        1,
        7,
        0,
        0,
        0,
        1,
        0,
        0,
        2,
        1,
        0,
        0,
        0,
        0,
        2,
        0,
        0,
        5,
        0,
        0,
        0,
        0,
        0,
        2,
        0,
        1,
        0,
        0,
        0,
        0,
        0,
        0,
        0,
        0,
        0,
        0,
        0,
        2,
        0,
        0,
        5,
        0,
        0,
        0,
        0,
        0,
        0,
        0,
        0,
        0,
        1,
        0,
        0,
        0,
        0,
        0,
        0,
        0,
        0,
        0,
        0,
        0,
        0,
        0,
        0,
        3,
        0,
        0,
        0,
        0,
        0,
        0,
        0,
        0,
        0,
        2,
        0,
        0,
        0,
        0,
        0,
        0,
        0,
        0,
        0,
        1,
        0,
        3,
        0,
        0,
        0,
        0,
        0,
        0,
        1,
        0,
        0,
        0,
        0,
        0,
        0,
        0,
        0,
        0,
        0,
        0,
        0,
        0,
        0,
        0,
        0,
        0,
        0
    ],
    "propagation_delay_min": 0.0,
    "propagation_delay_mean": 515.2276923076923,
    "propagation_delay_max": 3760.03,
    "reaction_time_min": 0.0,
    "reaction_time_mean": 515.2276923076923,
    "reaction_time_max": 3760.03,
    "betweenness_centrality": {
        "ROOT": 0.0,
        "3540252020": 0.008620689655172414,
        "2316293558": 0.0,
        "913517954": 0.0,
        "466028132": 0.00014992503748125936,
        "110855805": 0.0013493253373313343,
        "88861017": 0.0,
        "4624858456": 0.0,
        "1332562506": 0.0,
        "4897039492": 0.00014992503748125936,
        "156702369": 0.0,
        "2555646577": 0.0,
        "567626521": 0.00014992503748125936,
        "18911142": 0.00044977511244377805,
        "4817472013": 0.0,
        "2273636460": 0.0,
        "249442064": 0.0,
        "98534609": 0.0,
        "474202929": 0.0002998500749625187,
        "34570673": 0.0,
        "3018746955": 0.0,
        "239760871": 0.0007496251874062968,
        "98769374": 0.0,
        "3817001403": 0.0,
        "36598765": 0.0,
        "149492990": 0.0,
        "146566275": 0.0,
        "972909709": 0.0002998500749625187,
        "3885858198": 0.0,
        "1449729692": 0.00014992503748125936,
        "18014574": 0.0,
        "1066204172": 0.0,
        "4854641986": 0.0,
        "63152943": 0.0,
        "49311062": 0.0,
        "909115597": 0.0,
        "1145739655": 0.0,
        "2686010270": 0.0,
        "177182882": 0.0,
        "725025813695991808": 0.0,
        "710467381496303617": 0.0,
        "1909350781": 0.0002998500749625187,
        "634311232": 0.0,
        "705502643758628866": 0.0,
        "393190233": 0.0007496251874062968,
        "1406560290": 0.0,
        "29826440": 0.0,
        "3140848178": 0.0,
        "2724738831": 0.0,
        "3710642235": 0.0,
        "4769955501": 0.0,
        "1928814516": 0.0,
        "2945947649": 0.0,
        "591951432": 0.0,
        "347057474": 0.00014992503748125936,
        "552093372": 0.0,
        "95652521": 0.0,
        "705549682177658880": 0.0,
        "1046135256": 0.0,
        "3437193124": 0.0,
        "1076310283": 0.0,
        "2921371785": 0.0,
        "935013020": 0.0,
        "2493487567": 0.0,
        "1075681177": 0.0,
        "714199284627873792": 0.0,
        "203344437": 0.0,
        "503585510": 0.0,
        "350650434": 0.0,
        "119534385": 0.00044977511244377805,
        "48141381": 0.0,
        "2485175279": 0.0,
        "2887967069": 0.0,
        "146510317": 0.0,
        "2484804322": 0.0,
        "2447944212": 0.0,
        "4435806134": 0.0,
        "3214959652": 0.0,
        "76808845": 0.0,
        "187059363": 0.0002998500749625187,
        "3876731894": 0.0,
        "55381358": 0.0,
        "310114960": 0.0,
        "52141764": 0.0,
        "258329760": 0.0,
        "713032252251308033": 0.0,
        "68207839": 0.0,
        "705192824375869440": 0.0,
        "2556018119": 0.0,
        "502255227": 0.0002998500749625187,
        "45554802": 0.0,
        "208083510": 0.00044977511244377805,
        "2510389099": 0.0,
        "2268070920": 0.0,
        "4343200905": 0.0,
        "41862133": 0.0,
        "37090930": 0.0,
        "861301399": 0.0,
        "172255937": 0.00014992503748125936,
        "4883420969": 0.0,
        "140638175": 0.0,
        "716346272215666688": 0.0,
        "2654356639": 0.0,
        "531682712": 0.0,
        "4541258180": 0.0,
        "360076254": 0.0,
        "4100601437": 0.0,
        "4809747394": 0.0,
        "2720088115": 0.0,
        "1111034935": 0.0,
        "3419026493": 0.0,
        "4735616514": 0.0,
        "31953101": 0.0,
        "170050937": 0.0,
        "369312255": 0.0,
        "702946028840943616": 0.0,
        "3012168862": 0.0
    },
    "closeness_centrality": {
        "ROOT": 0.0,
        "3540252020": 0.008620689655172414,
        "2316293558": 0.011494252873563218,
        "913517954": 0.011494252873563218,
        "466028132": 0.011494252873563218,
        "110855805": 0.011494252873563218,
        "88861017": 0.011494252873563218,
        "4624858456": 0.011494252873563218,
        "1332562506": 0.01939655172413793,
        "4897039492": 0.011494252873563218,
        "156702369": 0.011494252873563218,
        "2555646577": 0.011494252873563218,
        "567626521": 0.011494252873563218,
        "18911142": 0.01293103448275862,
        "4817472013": 0.011494252873563218,
        "2273636460": 0.011494252873563218,
        "249442064": 0.011494252873563218,
        "98534609": 0.011494252873563218,
        "474202929": 0.011494252873563218,
        "34570673": 0.01293103448275862,
        "3018746955": 0.01293103448275862,
        "239760871": 0.011494252873563218,
        "98769374": 0.011494252873563218,
        "3817001403": 0.011494252873563218,
        "36598765": 0.01293103448275862,
        "149492990": 0.01293103448275862,
        "146566275": 0.011494252873563218,
        "972909709": 0.011494252873563218,
        "3885858198": 0.01293103448275862,
        "1449729692": 0.011494252873563218,
        "18014574": 0.01293103448275862,
        "1066204172": 0.011494252873563218,
        "4854641986": 0.01293103448275862,
        "63152943": 0.01293103448275862,
        "49311062": 0.011494252873563218,
        "909115597": 0.011494252873563218,
        "1145739655": 0.011494252873563218,
        "2686010270": 0.011494252873563218,
        "177182882": 0.011494252873563218,
        "725025813695991808": 0.01293103448275862,
        "710467381496303617": 0.01293103448275862,
        "1909350781": 0.011494252873563218,
        "634311232": 0.01293103448275862,
        "705502643758628866": 0.011494252873563218,
        "393190233": 0.011494252873563218,
        "1406560290": 0.01293103448275862,
        "29826440": 0.011494252873563218,
        "3140848178": 0.011494252873563218,
        "2724738831": 0.011494252873563218,
        "3710642235": 0.011494252873563218,
        "4769955501": 0.011494252873563218,
        "1928814516": 0.01293103448275862,
        "2945947649": 0.01293103448275862,
        "591951432": 0.011494252873563218,
        "347057474": 0.011494252873563218,
        "552093372": 0.011494252873563218,
        "95652521": 0.01293103448275862,
        "705549682177658880": 0.01293103448275862,
        "1046135256": 0.011494252873563218,
        "3437193124": 0.01293103448275862,
        "1076310283": 0.011494252873563218,
        "2921371785": 0.011494252873563218,
        "935013020": 0.011494252873563218,
        "2493487567": 0.011494252873563218,
        "1075681177": 0.011494252873563218,
        "714199284627873792": 0.011494252873563218,
        "203344437": 0.01293103448275862,
        "503585510": 0.011494252873563218,
        "350650434": 0.011494252873563218,
        "119534385": 0.011494252873563218,
        "48141381": 0.011494252873563218,
        "2485175279": 0.01293103448275862,
        "2887967069": 0.011494252873563218,
        "146510317": 0.011494252873563218,
        "2484804322": 0.01293103448275862,
        "2447944212": 0.01293103448275862,
        "4435806134": 0.011494252873563218,
        "3214959652": 0.01293103448275862,
        "76808845": 0.011494252873563218,
        "187059363": 0.011494252873563218,
        "3876731894": 0.011494252873563218,
        "55381358": 0.01293103448275862,
        "310114960": 0.01293103448275862,
        "52141764": 0.011494252873563218,
        "258329760": 0.011494252873563218,
        "713032252251308033": 0.011494252873563218,
        "68207839": 0.011494252873563218,
        "705192824375869440": 0.01293103448275862,
        "2556018119": 0.011494252873563218,
        "502255227": 0.013793103448275862,
        "45554802": 0.011494252873563218,
        "208083510": 0.011494252873563218,
        "2510389099": 0.011494252873563218,
        "2268070920": 0.01293103448275862,
        "4343200905": 0.011494252873563218,
        "41862133": 0.011494252873563218,
        "37090930": 0.011494252873563218,
        "861301399": 0.01293103448275862,
        "172255937": 0.011494252873563218,
        "4883420969": 0.011494252873563218,
        "140638175": 0.01293103448275862,
        "716346272215666688": 0.01293103448275862,
        "2654356639": 0.011494252873563218,
        "531682712": 0.01293103448275862,
        "4541258180": 0.01293103448275862,
        "360076254": 0.011494252873563218,
        "4100601437": 0.011494252873563218,
        "4809747394": 0.014367816091954023,
        "2720088115": 0.01293103448275862,
        "1111034935": 0.01293103448275862,
        "3419026493": 0.01293103448275862,
        "4735616514": 0.011494252873563218,
        "31953101": 0.01293103448275862,
        "170050937": 0.011494252873563218,
        "369312255": 0.011494252873563218,
        "702946028840943616": 0.011494252873563218,
        "3012168862": 0.01293103448275862
    }
}