{
    "number_of_nodes": 165.0,
    "number_of_edges": 166.0,
    "cascade_size": 164.0,
    "tree_depth": 3.0,
    "in_degree_distribution": [
        0,
        1,
        1,
        1,
        1,
        1,
        1,
        1,
        1,
        1,
        1,
        1,
        1,
        1,
        1,
        1,
        1,
        1,
        1,
        1,
        1,
        1,
        1,
        1,
        1,
        2,
        1,
        1,
        1,
        1,
        1,
        1,
        1,
        1,
        1,
        1,
        1,
        1,
        1,
        1,
        1,
        1,
        1,
        1,
        1,
        1,
        1,
        1,
        1,
        1,
        1,
        1,
        1,
        1,
        1,
        1,
        1,
        1,
        1,
        1,
        1,
        1,
        1,
        1,
        1,
        1,
        1,
        1,
        1,
        1,
        1,
        1,
        1,
        1,
        1,
        1,
        1,
        1,
        1,
        1,
        1,
        1,
        1,
        1,
        1,
        1,
        1,
        1,
        1,
        1,
        1,
        1,
        1,
        1,
        1,
        1,
        1,
        1,
        1,
        1,
        1,
        1,
        1,
        1,
        1,
        1,
        1,
        1,
        1,
        1,
        1,
        1,
        1,
        1,
        1,
        1,
        1,
        1,
        1,
        1,
        1,
        1,
        1,
        1,
        1,
        1,
        2,
        1,
        1,
        1,
        1,
        1,
        1,
        1,
        1,
        1,
        1,
        1,
        1,
        1,
        1,
        1,
        1,
        1,
        1,
        1,
        1,
        1,
        1,
        1,
        1,
        1,
        1,
        1,
        1,
        1,
        1,
        1,
        1,
        1,
        1,
        1,
        1,
        1,
        1
    ],
    "out_degree_distribution": [
        1,
        141,
        0,
        0,
        0,
        0,
        0,
        0,
        0,
        0,
        0,
        0,
        1,
        0,
        0,
        0,
        1,
        0,
        0,
        0,
        0,
        0,
        0,
        0,
        0,
        0,
        0,
        0,
        0,
        0,
        0,
        0,
        2,
        0,
        0,
        0,
        0,
        0,
        0,
        0,
        0,
        0,
        0,
        0,
        0,
        0,
        0,
        0,
        0,
        0,
        0,
        1,
        0,
        5,
        0,
        0,
        0,
        5,
        0,
        0,
        0,
        0,
        2,
        0,
        0,
        1,
        0,
        0,
        0,
        0,
        0,
        0,
        0,
        1,
        1,
        2,
        0,
        0,
        0,
        0,
        0,
        0,
        0,
        0,
        0,
        0,
        0,
        0,
        0,
        0,
        0,
        0,
        0,
        0,
        0,
        0,
        0,
        0,
        0,
        0,
        0,
        0,
        0,
        0,
        0,
        0,
        0,
        0,
        0,
        0,
        0,
        0,
        0,
        0,
        0,
        0,
        0,
        0,
        0,
        0,
        0,
        0,
        0,
        1,
        0,
        0,
        0,
        0,
        0,
        0,
        0,
        0,
        0,
        0,
        0,
        0,
        0,
        0,
        0,
        0,
        0,
        0,
        0,
        0,
        0,
        0,
        0,
        0,
        0,
        0,
        0,
        0,
        0,
        0,
        0,
        0,
        0,
        1,
        0,
        0,
        0,
        0,
        0,
        0,
        0
    ],
    "propagation_delay_min": 0.0,
    "propagation_delay_mean": 2977.7406024096385,
    "propagation_delay_max": 27809.13,
    "reaction_time_min": 0.0,
    "reaction_time_mean": 2977.7406024096385,
    "reaction_time_max": 27809.13,
    "betweenness_centrality": {
        "ROOT": 0.0,
        "462104542": 0.006097560975609756,
        "1630586989": 0.0,
        "406348956": 0.0,
        "52759650": 0.0,
        "712547301529673728": 0.0,
        "2386502114": 0.0,
        "29237747": 0.0,
        "4705133474": 0.0,
        "20502577": 0.0,
        "708485128800997376": 0.0,
        "2165653659": 0.0,
        "100332944": 7.481669908723627e-05,
        "1855170788": 0.0,
        "4887155859": 0.0,
        "2675446555": 0.0,
        "11228322": 0.0,
        "40290487": 0.0,
        "555348271": 0.0,
        "4180352153": 0.0,
        "327004121": 0.0,
        "1517261017": 0.0,
        "33977442": 0.0,
        "2479202503": 0.0,
        "3303740978": 0.0,
        "993800743": 0.0,
        "730756428": 0.0,
        "4261082614": 0.0,
        "745109156": 0.0,
        "40614984": 0.0,
        "180728640": 0.0,
        "1902400610": 0.0,
        "4064968773": 0.00014963339817447254,
        "90286882": 0.0,
        "702826401947254784": 0.0,
        "615360297": 0.0,
        "83587516": 0.0,
        "3581716035": 0.0,
        "4786132700": 0.0,
        "2629104117": 0.0,
        "779241350": 0.0,
        "502559275": 0.0,
        "538916469": 0.0,
        "26791522": 0.0,
        "38017472": 0.0,
        "4179814341": 0.0,
        "3318179923": 0.0,
        "1904454054": 0.0,
        "526543401": 0.0,
        "345644480": 0.0,
        "2169509437": 0.0,
        "757345172": 7.481669908723627e-05,
        "261098344": 0.0,
        "1338047336": 0.0002992667963489451,
        "113209462": 0.0,
        "241033134": 0.0,
        "2596413645": 0.0,
        "940368062": 0.00037408349543618133,
        "1250323009": 0.0,
        "516103610": 0.0,
        "57528178": 0.0,
        "238015192": 0.0,
        "32765764": 0.00014963339817447254,
        "2978209336": 0.0,
        "4836728134": 0.0,
        "33949018": 7.481669908723627e-05,
        "335043068": 0.0,
        "156702369": 0.0,
        "2248442846": 0.0,
        "2334312147": 0.0,
        "196611495": 0.0,
        "476811284": 0.0,
        "788352756": 0.0,
        "1107918674": 7.481669908723627e-05,
        "1049681827": 7.481669908723627e-05,
        "3296504462": 0.00014963339817447254,
        "3424489361": 0.0,
        "4351416912": 0.0,
        "115377042": 0.0,
        "695074047223160832": 0.0,
        "423745681": 0.0,
        "1905556350": 0.0,
        "2332158583": 0.0,
        "1403726954": 0.0,
        "3331932665": 0.0,
        "4456348512": 0.0,
        "384330450": 0.0,
        "4721727745": 0.0,
        "611350965": 0.0,
        "2966375290": 0.0,
        "3248832505": 0.0,
        "3165315405": 0.0,
        "2384136884": 0.0,
        "52426384": 0.0,
        "4739845481": 0.0,
        "41447377": 0.0,
        "298034527": 0.0,
        "4874129992": 0.0,
        "891114542": 0.0,
        "1596575564": 0.0,
        "814429434": 0.0,
        "69190453": 0.0,
        "3424241421": 0.0,
        "1372786812": 0.0,
        "4587580579": 0.0,
        "2894032402": 0.0,
        "831090432": 0.0,
        "4845303771": 0.0,
        "707242468": 0.0,
        "616642919": 0.0,
        "2935608063": 0.0,
        "728219153950183424": 0.0,
        "2369213666": 0.0,
        "20218885": 0.0,
        "4596637336": 0.0,
        "311140916": 0.0,
        "18315727": 0.0,
        "155394343": 0.0,
        "1342778461": 0.0,
        "306402067": 0.0,
        "1268570407": 0.0,
        "2543427014": 0.0,
        "1631841212": 0.0,
        "390910877": 7.481669908723627e-05,
        "601076863": 0.0,
        "811514036": 0.0,
        "175174041": 0.0,
        "75325152": 0.0,
        "485960927": 0.0,
        "2312387600": 0.0,
        "491748291": 0.0,
        "22272119": 0.0,
        "4273596738": 0.0,
        "4659654224": 0.0,
        "4019065804": 0.0,
        "526346146": 0.0,
        "74247792": 0.0,
        "1564676498": 0.0,
        "33410754": 0.0,
        "1909314529": 0.0,
        "900187770": 0.0,
        "2430626287": 0.0,
        "707591424200445952": 0.0,
        "182265955": 0.0,
        "250952665": 0.0,
        "383863452": 0.0,
        "184027478": 0.0,
        "2369506560": 0.0,
        "3173651177": 0.0,
        "1148372244": 0.0,
        "2642847487": 0.0,
        "22456513": 0.0,
        "1968961112": 0.0,
        "4064541252": 0.0,
        "3395283258": 0.0,
        "17145020": 0.0,
        "22993909": 0.0,
        "135247359": 7.481669908723627e-05,
        "234466998": 0.0,
        "90966455": 0.0,
        "217285732": 0.0,
        "525002011": 0.0,
        "278163796": 0.0,
        "89655673": 0.0,
        "609124089": 0.0
    },
    "closeness_centrality": {
        "ROOT": 0.0,
        "462104542": 0.006097560975609756,
        "1630586989": 0.008130081300813007,
        "406348956": 0.008130081300813007,
        "52759650": 0.008130081300813007,
        "712547301529673728": 0.008130081300813007,
        "2386502114": 0.008130081300813007,
        "29237747": 0.008130081300813007,
        "4705133474": 0.008130081300813007,
        "20502577": 0.008130081300813007,
        "708485128800997376": 0.008130081300813007,
        "2165653659": 0.008130081300813007,
        "100332944": 0.008130081300813007,
        "1855170788": 0.008130081300813007,
        "4887155859": 0.008130081300813007,
        "2675446555": 0.008130081300813007,
        "11228322": 0.008130081300813007,
        "40290487": 0.008130081300813007,
        "555348271": 0.008130081300813007,
        "4180352153": 0.008130081300813007,
        "327004121": 0.008130081300813007,
        "1517261017": 0.008130081300813007,
        "33977442": 0.008130081300813007,
        "2479202503": 0.008130081300813007,
        "3303740978": 0.008130081300813007,
        "993800743": 0.01371951219512195,
        "730756428": 0.008130081300813007,
        "4261082614": 0.008130081300813007,
        "745109156": 0.008130081300813007,
        "40614984": 0.008130081300813007,
        "180728640": 0.008130081300813007,
        "1902400610": 0.008130081300813007,
        "4064968773": 0.008130081300813007,
        "90286882": 0.008130081300813007,
        "702826401947254784": 0.008130081300813007,
        "615360297": 0.008130081300813007,
        "83587516": 0.009146341463414634,
        "3581716035": 0.008130081300813007,
        "4786132700": 0.008130081300813007,
        "2629104117": 0.008130081300813007,
        "779241350": 0.008130081300813007,
        "502559275": 0.008130081300813007,
        "538916469": 0.008130081300813007,
        "26791522": 0.008130081300813007,
        "38017472": 0.008130081300813007,
        "4179814341": 0.008130081300813007,
        "3318179923": 0.008130081300813007,
        "1904454054": 0.008130081300813007,
        "526543401": 0.008130081300813007,
        "345644480": 0.008130081300813007,
        "2169509437": 0.008130081300813007,
        "757345172": 0.008130081300813007,
        "261098344": 0.008130081300813007,
        "1338047336": 0.008130081300813007,
        "113209462": 0.009146341463414634,
        "241033134": 0.008130081300813007,
        "2596413645": 0.008130081300813007,
        "940368062": 0.008130081300813007,
        "1250323009": 0.008130081300813007,
        "516103610": 0.009146341463414634,
        "57528178": 0.008130081300813007,
        "238015192": 0.008130081300813007,
        "32765764": 0.008130081300813007,
        "2978209336": 0.009146341463414634,
        "4836728134": 0.008130081300813007,
        "33949018": 0.008130081300813007,
        "335043068": 0.008130081300813007,
        "156702369": 0.008130081300813007,
        "2248442846": 0.009146341463414634,
        "2334312147": 0.009146341463414634,
        "196611495": 0.009146341463414634,
        "476811284": 0.008130081300813007,
        "788352756": 0.008130081300813007,
        "1107918674": 0.008130081300813007,
        "1049681827": 0.008130081300813007,
        "3296504462": 0.008130081300813007,
        "3424489361": 0.008130081300813007,
        "4351416912": 0.008130081300813007,
        "115377042": 0.008130081300813007,
        "695074047223160832": 0.008130081300813007,
        "423745681": 0.008130081300813007,
        "1905556350": 0.008130081300813007,
        "2332158583": 0.009146341463414634,
        "1403726954": 0.008130081300813007,
        "3331932665": 0.009146341463414634,
        "4456348512": 0.008130081300813007,
        "384330450": 0.008130081300813007,
        "4721727745": 0.008130081300813007,
        "611350965": 0.008130081300813007,
        "2966375290": 0.008130081300813007,
        "3248832505": 0.008130081300813007,
        "3165315405": 0.008130081300813007,
        "2384136884": 0.008130081300813007,
        "52426384": 0.008130081300813007,
        "4739845481": 0.008130081300813007,
        "41447377": 0.009146341463414634,
        "298034527": 0.008130081300813007,
        "4874129992": 0.009146341463414634,
        "891114542": 0.008130081300813007,
        "1596575564": 0.008130081300813007,
        "814429434": 0.008130081300813007,
        "69190453": 0.008130081300813007,
        "3424241421": 0.008130081300813007,
        "1372786812": 0.008130081300813007,
        "4587580579": 0.008130081300813007,
        "2894032402": 0.008130081300813007,
        "831090432": 0.009146341463414634,
        "4845303771": 0.008130081300813007,
        "707242468": 0.008130081300813007,
        "616642919": 0.009146341463414634,
        "2935608063": 0.008130081300813007,
        "728219153950183424": 0.008130081300813007,
        "2369213666": 0.008130081300813007,
        "20218885": 0.008130081300813007,
        "4596637336": 0.009146341463414634,
        "311140916": 0.008130081300813007,
        "18315727": 0.008130081300813007,
        "155394343": 0.008130081300813007,
        "1342778461": 0.009146341463414634,
        "306402067": 0.008130081300813007,
        "1268570407": 0.009146341463414634,
        "2543427014": 0.008130081300813007,
        "1631841212": 0.008130081300813007,
        "390910877": 0.008130081300813007,
        "601076863": 0.008130081300813007,
        "811514036": 0.008130081300813007,
        "175174041": 0.01371951219512195,
        "75325152": 0.008130081300813007,
        "485960927": 0.008130081300813007,
        "2312387600": 0.008130081300813007,
        "491748291": 0.008130081300813007,
        "22272119": 0.008130081300813007,
        "4273596738": 0.009146341463414634,
        "4659654224": 0.008130081300813007,
        "4019065804": 0.008130081300813007,
        "526346146": 0.008130081300813007,
        "74247792": 0.008130081300813007,
        "1564676498": 0.008130081300813007,
        "33410754": 0.008130081300813007,
        "1909314529": 0.008130081300813007,
        "900187770": 0.008130081300813007,
        "2430626287": 0.009146341463414634,
        "707591424200445952": 0.008130081300813007,
        "182265955": 0.008130081300813007,
        "250952665": 0.009146341463414634,
        "383863452": 0.008130081300813007,
        "184027478": 0.008130081300813007,
        "2369506560": 0.008130081300813007,
        "3173651177": 0.008130081300813007,
        "1148372244": 0.008130081300813007,
        "2642847487": 0.009146341463414634,
        "22456513": 0.008130081300813007,
        "1968961112": 0.008130081300813007,
        "4064541252": 0.008130081300813007,
        "3395283258": 0.008130081300813007,
        "17145020": 0.009146341463414634,
        "22993909": 0.008130081300813007,
        "135247359": 0.008130081300813007,
        "234466998": 0.009146341463414634,
        "90966455": 0.008130081300813007,
        "217285732": 0.008130081300813007,
        "525002011": 0.008130081300813007,
        "278163796": 0.008130081300813007,
        "89655673": 0.008130081300813007,
        "609124089": 0.008130081300813007
    }
}