{
    "number_of_nodes": 115.0,
    "number_of_edges": 114.0,
    "cascade_size": 114.0,
    "tree_depth": 3.0,
    "in_degree_distribution": [
        0,
        1,
        1,
        1,
        1,
        1,
        1,
        1,
        1,
        1,
        1,
        1,
        1,
        1,
        1,
        1,
        1,
        1,
        1,
        1,
        1,
        1,
        1,
        1,
        1,
        1,
        1,
        1,
        1,
        1,
        1,
        1,
        1,
        1,
        1,
        1,
        1,
        1,
        1,
        1,
        1,
        1,
        1,
        1,
        1,
        1,
        1,
        1,
        1,
        1,
        1,
        1,
        1,
        1,
        1,
        1,
        1,
        1,
        1,
        1,
        1,
        1,
        1,
        1,
        1,
        1,
        1,
        1,
        1,
        1,
        1,
        1,
        1,
        1,
        1,
        1,
        1,
        1,
        1,
        1,
        1,
        1,
        1,
        1,
        1,
        1,
        1,
        1,
        1,
        1,
        1,
        1,
        1,
        1,
        1,
        1,
        1,
        1,
        1,
        1,
        1,
        1,
        1,
        1,
        1,
        1,
        1,
        1,
        1,
        1,
        1,
        1,
        1,
        1,
        1
    ],
    "out_degree_distribution": [
        1,
        112,
        0,
        0,
        0,
        0,
        0,
        0,
        0,
        0,
        0,
        0,
        0,
        0,
        0,
        0,
        0,
        0,
        0,
        0,
        0,
        0,
        0,
        0,
        0,
        0,
        0,
        0,
        0,
        0,
        0,
        0,
        0,
        0,
        0,
        0,
        0,
        0,
        0,
        0,
        0,
        0,
        0,
        0,
        0,
        0,
        0,
        0,
        0,
        0,
        0,
        0,
        0,
        0,
        0,
        0,
        0,
        0,
        0,
        0,
        0,
        0,
        0,
        0,
        0,
        0,
        0,
        0,
        0,
        0,
        0,
        1,
        0,
        0,
        0,
        0,
        0,
        0,
        0,
        0,
        0,
        0,
        0,
        0,
        0,
        0,
        0,
        0,
        0,
        0,
        0,
        0,
        0,
        0,
        0,
        0,
        0,
        0,
        0,
        0,
        0,
        0,
        0,
        0,
        0,
        0,
        0,
        0,
        0,
        0,
        0,
        0,
        0,
        0,
        0
    ],
    "propagation_delay_min": 0.0,
    "propagation_delay_mean": 73.75473684210526,
    "propagation_delay_max": 1286.13,
    "reaction_time_min": 0.0,
    "reaction_time_mean": 73.75473684210526,
    "reaction_time_max": 1286.13,
    "betweenness_centrality": {
        "ROOT": 0.0,
        "51241574": 0.008771929824561403,
        "435035276": 0.0,
        "537478538": 0.0,
        "15738612": 0.0,
        "1020058453": 0.0,
        "41655668": 0.0,
        "56609174": 0.0,
        "999588744": 0.0,
        "249078816": 0.0,
        "303418470": 0.0,
        "545528259": 0.0,
        "757173062": 0.0,
        "439720206": 0.0,
        "1113177727": 0.0,
        "215460413": 0.0,
        "87464413": 0.0,
        "108556027": 0.0,
        "49800332": 0.0,
        "14281980": 0.0,
        "395514224": 0.0,
        "2823004047": 0.0,
        "788018329": 0.0,
        "143246253": 0.0,
        "207420832": 0.0,
        "383779972": 0.0,
        "245577571": 0.0,
        "11740172": 0.0,
        "129164948": 0.0,
        "347632274": 0.0,
        "2359256510": 0.0,
        "271361465": 0.0,
        "60685889": 0.0,
        "476522226": 0.0,
        "21159536": 0.0,
        "377511373": 0.0,
        "2376768615": 0.0,
        "168757818": 0.0,
        "337112001": 0.0,
        "217106184": 0.0,
        "52834959": 0.0,
        "47047946": 0.0,
        "969021517": 0.0,
        "121812371": 0.0,
        "2750570973": 0.0,
        "442398847": 0.0,
        "395997951": 0.0,
        "97989357": 0.0,
        "290840403": 0.0,
        "2383954135": 0.0,
        "35976790": 0.0,
        "22526181": 0.0,
        "2593165068": 0.0,
        "394744306": 0.0,
        "49884490": 0.0,
        "10861402": 0.0,
        "173119587": 0.0,
        "24395167": 0.0,
        "67706546": 0.0,
        "422050952": 0.0,
        "19355955": 0.0,
        "2791953405": 0.0,
        "124290595": 0.0,
        "37238868": 0.0,
        "36690325": 0.0,
        "218150364": 0.0,
        "2561724956": 0.0,
        "14186393": 0.0,
        "2569487083": 0.0,
        "480586426": 0.0,
        "32792712": 0.0,
        "97622779": 0.0001552553951249806,
        "8980312": 0.0,
        "20213865": 0.0,
        "109579523": 0.0,
        "2536540613": 0.0,
        "508366582": 0.0,
        "168577684": 0.0,
        "107497796": 0.0,
        "495454106": 0.0,
        "2408876371": 0.0,
        "443294664": 0.0,
        "21479865": 0.0,
        "426083802": 0.0,
        "109425543": 0.0,
        "312616238": 0.0,
        "81983412": 0.0,
        "264017858": 0.0,
        "45998359": 0.0,
        "2880778944": 0.0,
        "86415799": 0.0,
        "2229848017": 0.0,
        "531358356": 0.0,
        "56589074": 0.0,
        "625751427": 0.0,
        "1326634382": 0.0,
        "90545133": 0.0,
        "2855706130": 0.0,
        "2334673819": 0.0,
        "275942684": 0.0,
        "21643769": 0.0,
        "775923356": 0.0,
        "53983654": 0.0,
        "24083719": 0.0,
        "865217299": 0.0,
        "242849343": 0.0,
        "174539199": 0.0,
        "1512120685": 0.0,
        "40961805": 0.0,
        "828068220": 0.0,
        "40574341": 0.0,
        "48654466": 0.0,
        "2464341842": 0.0,
        "32377262": 0.0,
        "2383567866": 0.0
    },
    "closeness_centrality": {
        "ROOT": 0.0,
        "51241574": 0.008771929824561403,
        "435035276": 0.011695906432748537,
        "537478538": 0.011695906432748537,
        "15738612": 0.011695906432748537,
        "1020058453": 0.011695906432748537,
        "41655668": 0.011695906432748537,
        "56609174": 0.011695906432748537,
        "999588744": 0.011695906432748537,
        "249078816": 0.011695906432748537,
        "303418470": 0.011695906432748537,
        "545528259": 0.011695906432748537,
        "757173062": 0.011695906432748537,
        "439720206": 0.011695906432748537,
        "1113177727": 0.011695906432748537,
        "215460413": 0.011695906432748537,
        "87464413": 0.011695906432748537,
        "108556027": 0.011695906432748537,
        "49800332": 0.011695906432748537,
        "14281980": 0.011695906432748537,
        "395514224": 0.011695906432748537,
        "2823004047": 0.011695906432748537,
        "788018329": 0.011695906432748537,
        "143246253": 0.011695906432748537,
        "207420832": 0.011695906432748537,
        "383779972": 0.011695906432748537,
        "245577571": 0.011695906432748537,
        "11740172": 0.011695906432748537,
        "129164948": 0.011695906432748537,
        "347632274": 0.011695906432748537,
        "2359256510": 0.011695906432748537,
        "271361465": 0.011695906432748537,
        "60685889": 0.011695906432748537,
        "476522226": 0.011695906432748537,
        "21159536": 0.011695906432748537,
        "377511373": 0.011695906432748537,
        "2376768615": 0.011695906432748537,
        "168757818": 0.011695906432748537,
        "337112001": 0.011695906432748537,
        "217106184": 0.011695906432748537,
        "52834959": 0.011695906432748537,
        "47047946": 0.011695906432748537,
        "969021517": 0.011695906432748537,
        "121812371": 0.011695906432748537,
        "2750570973": 0.011695906432748537,
        "442398847": 0.011695906432748537,
        "395997951": 0.011695906432748537,
        "97989357": 0.011695906432748537,
        "290840403": 0.011695906432748537,
        "2383954135": 0.011695906432748537,
        "35976790": 0.011695906432748537,
        "22526181": 0.011695906432748537,
        "2593165068": 0.011695906432748537,
        "394744306": 0.011695906432748537,
        "49884490": 0.011695906432748537,
        "10861402": 0.011695906432748537,
        "173119587": 0.011695906432748537,
        "24395167": 0.011695906432748537,
        "67706546": 0.011695906432748537,
        "422050952": 0.011695906432748537,
        "19355955": 0.011695906432748537,
        "2791953405": 0.011695906432748537,
        "124290595": 0.011695906432748537,
        "37238868": 0.011695906432748537,
        "36690325": 0.011695906432748537,
        "218150364": 0.011695906432748537,
        "2561724956": 0.011695906432748537,
        "14186393": 0.011695906432748537,
        "2569487083": 0.011695906432748537,
        "480586426": 0.011695906432748537,
        "32792712": 0.011695906432748537,
        "97622779": 0.011695906432748537,
        "8980312": 0.011695906432748537,
        "20213865": 0.011695906432748537,
        "109579523": 0.011695906432748537,
        "2536540613": 0.011695906432748537,
        "508366582": 0.011695906432748537,
        "168577684": 0.011695906432748537,
        "107497796": 0.011695906432748537,
        "495454106": 0.011695906432748537,
        "2408876371": 0.011695906432748537,
        "443294664": 0.011695906432748537,
        "21479865": 0.011695906432748537,
        "426083802": 0.011695906432748537,
        "109425543": 0.011695906432748537,
        "312616238": 0.011695906432748537,
        "81983412": 0.011695906432748537,
        "264017858": 0.011695906432748537,
        "45998359": 0.011695906432748537,
        "2880778944": 0.011695906432748537,
        "86415799": 0.011695906432748537,
        "2229848017": 0.011695906432748537,
        "531358356": 0.011695906432748537,
        "56589074": 0.011695906432748537,
        "625751427": 0.011695906432748537,
        "1326634382": 0.011695906432748537,
        "90545133": 0.011695906432748537,
        "2855706130": 0.011695906432748537,
        "2334673819": 0.011695906432748537,
        "275942684": 0.011695906432748537,
        "21643769": 0.011695906432748537,
        "775923356": 0.011695906432748537,
        "53983654": 0.011695906432748537,
        "24083719": 0.013157894736842105,
        "865217299": 0.011695906432748537,
        "242849343": 0.011695906432748537,
        "174539199": 0.011695906432748537,
        "1512120685": 0.011695906432748537,
        "40961805": 0.011695906432748537,
        "828068220": 0.011695906432748537,
        "40574341": 0.011695906432748537,
        "48654466": 0.011695906432748537,
        "2464341842": 0.011695906432748537,
        "32377262": 0.011695906432748537,
        "2383567866": 0.011695906432748537
    }
}