{
    "number_of_nodes": 113.0,
    "number_of_edges": 113.0,
    "cascade_size": 112.0,
    "tree_depth": 3.0,
    "in_degree_distribution": [
        0,
        1,
        1,
        1,
        1,
        1,
        1,
        1,
        1,
        1,
        1,
        1,
        1,
        1,
        1,
        1,
        1,
        1,
        1,
        1,
        1,
        1,
        1,
        1,
        1,
        1,
        1,
        1,
        1,
        1,
        1,
        1,
        1,
        1,
        1,
        1,
        1,
        1,
        1,
        1,
        1,
        1,
        1,
        1,
        1,
        1,
        1,
        1,
        1,
        1,
        1,
        1,
        2,
        1,
        1,
        1,
        1,
        1,
        1,
        1,
        1,
        1,
        1,
        1,
        1,
        1,
        1,
        1,
        1,
        1,
        1,
        1,
        1,
        1,
        1,
        1,
        1,
        1,
        1,
        1,
        1,
        1,
        1,
        1,
        1,
        1,
        1,
        1,
        1,
        1,
        1,
        1,
        1,
        1,
        1,
        1,
        1,
        1,
        1,
        1,
        1,
        1,
        1,
        1,
        1,
        1,
        1,
        1,
        1,
        1,
        1,
        1,
        1
    ],
    "out_degree_distribution": [
        1,
        108,
        0,
        0,
        0,
        0,
        0,
        0,
        1,
        0,
        0,
        0,
        0,
        0,
        0,
        0,
        0,
        0,
        0,
        0,
        0,
        0,
        0,
        0,
        0,
        0,
        0,
        0,
        0,
        0,
        0,
        0,
        0,
        0,
        0,
        0,
        0,
        0,
        0,
        0,
        0,
        0,
        0,
        0,
        0,
        0,
        0,
        0,
        0,
        0,
        0,
        0,
        0,
        0,
        0,
        0,
        1,
        0,
        0,
        0,
        0,
        0,
        0,
        0,
        0,
        0,
        0,
        0,
        0,
        0,
        0,
        0,
        0,
        0,
        0,
        0,
        0,
        0,
        0,
        0,
        0,
        0,
        0,
        0,
        0,
        0,
        0,
        0,
        0,
        0,
        0,
        0,
        0,
        0,
        0,
        0,
        0,
        0,
        1,
        0,
        0,
        1,
        0,
        0,
        0,
        0,
        0,
        0,
        0,
        0,
        0,
        0,
        0
    ],
    "propagation_delay_min": 0.0,
    "propagation_delay_mean": 162.3196460176991,
    "propagation_delay_max": 5565.42,
    "reaction_time_min": 0.0,
    "reaction_time_mean": 162.3196460176991,
    "reaction_time_max": 5565.42,
    "betweenness_centrality": {
        "ROOT": 0.0,
        "64643056": 0.008928571428571428,
        "116493791": 0.0,
        "2828920482": 0.0,
        "123030122": 0.0,
        "23143326": 0.0,
        "328586464": 0.0,
        "174590936": 0.0,
        "61149021": 0.0,
        "2783538092": 0.0,
        "121875959": 0.0,
        "1559083963": 0.0,
        "130463591": 0.0,
        "1242171468": 0.0,
        "1538077100": 0.0,
        "2315880906": 0.0,
        "633614191": 0.0,
        "246351069": 0.0,
        "326142499": 0.0,
        "2650463314": 0.0,
        "2703574544": 0.0,
        "916340754": 0.0,
        "1431876728": 0.0,
        "390801303": 0.0,
        "2266108082": 0.0,
        "793226382": 0.0,
        "22133083": 0.0,
        "292517363": 0.0,
        "1265174228": 0.0,
        "2798848065": 0.0,
        "202053116": 0.0,
        "901092264": 0.0,
        "177362867": 0.0,
        "2573215164": 0.0,
        "480392039": 0.0,
        "46713815": 0.0,
        "2184482493": 0.0,
        "428543269": 0.0,
        "372257495": 0.0,
        "210356416": 0.0,
        "125227659": 0.0,
        "2733508533": 0.0,
        "18892635": 0.0,
        "130307742": 0.0,
        "485954672": 0.0,
        "428892165": 0.0,
        "36677989": 0.0,
        "1673260717": 0.0,
        "315897575": 0.0,
        "307068082": 0.0,
        "2380835600": 0.0,
        "579962917": 0.0,
        "61125151": 0.0,
        "221803717": 0.0,
        "2300445898": 0.0,
        "988216526": 0.0,
        "162594551": 0.00016087516087516087,
        "1431889375": 0.0,
        "132687861": 0.0,
        "2565616602": 0.0,
        "767800": 0.0,
        "252860539": 0.0,
        "2188545410": 0.0,
        "45837736": 0.0,
        "132656546": 0.0,
        "74954965": 0.0,
        "272598655": 0.0,
        "2502883539": 0.0,
        "544428050": 0.0,
        "756158490": 0.0,
        "1193125254": 0.0,
        "985543027": 0.0,
        "2153781255": 0.0,
        "1073802067": 0.0,
        "237903360": 0.0,
        "46888830": 0.0,
        "823749043": 0.0,
        "2753468812": 0.0,
        "25860925": 0.0,
        "132306981": 0.0,
        "2841791664": 0.0,
        "543567716": 0.0,
        "1705297002": 0.0,
        "1111125584": 0.0,
        "55167998": 0.0,
        "2365305244": 0.0,
        "2775836165": 0.0,
        "517883933": 0.0,
        "1366541438": 0.0,
        "63492240": 0.0,
        "277645188": 0.0,
        "466786036": 0.0,
        "1468968181": 0.0,
        "37440873": 0.0,
        "48654466": 0.0,
        "214842977": 0.0,
        "1208186910": 0.0,
        "2720128089": 0.0,
        "606316616": 0.00016087516087516087,
        "145312730": 0.0,
        "485675463": 0.0,
        "111514588": 0.00016087516087516087,
        "351864017": 0.0,
        "596151434": 0.0,
        "2746249391": 0.0,
        "1097615942": 0.0,
        "337761893": 0.0,
        "1140237624": 0.0,
        "2754259598": 0.0,
        "130291190": 0.0,
        "975505339": 0.0,
        "630485446": 0.0,
        "282894960": 0.0
    },
    "closeness_centrality": {
        "ROOT": 0.0,
        "64643056": 0.008928571428571428,
        "116493791": 0.011904761904761904,
        "2828920482": 0.011904761904761904,
        "123030122": 0.011904761904761904,
        "23143326": 0.011904761904761904,
        "328586464": 0.011904761904761904,
        "174590936": 0.011904761904761904,
        "61149021": 0.011904761904761904,
        "2783538092": 0.011904761904761904,
        "121875959": 0.011904761904761904,
        "1559083963": 0.011904761904761904,
        "130463591": 0.011904761904761904,
        "1242171468": 0.011904761904761904,
        "1538077100": 0.011904761904761904,
        "2315880906": 0.011904761904761904,
        "633614191": 0.011904761904761904,
        "246351069": 0.011904761904761904,
        "326142499": 0.011904761904761904,
        "2650463314": 0.011904761904761904,
        "2703574544": 0.011904761904761904,
        "916340754": 0.011904761904761904,
        "1431876728": 0.011904761904761904,
        "390801303": 0.011904761904761904,
        "2266108082": 0.011904761904761904,
        "793226382": 0.011904761904761904,
        "22133083": 0.011904761904761904,
        "292517363": 0.011904761904761904,
        "1265174228": 0.011904761904761904,
        "2798848065": 0.011904761904761904,
        "202053116": 0.011904761904761904,
        "901092264": 0.011904761904761904,
        "177362867": 0.011904761904761904,
        "2573215164": 0.011904761904761904,
        "480392039": 0.011904761904761904,
        "46713815": 0.011904761904761904,
        "2184482493": 0.011904761904761904,
        "428543269": 0.011904761904761904,
        "372257495": 0.011904761904761904,
        "210356416": 0.011904761904761904,
        "125227659": 0.011904761904761904,
        "2733508533": 0.011904761904761904,
        "18892635": 0.011904761904761904,
        "130307742": 0.011904761904761904,
        "485954672": 0.011904761904761904,
        "428892165": 0.011904761904761904,
        "36677989": 0.011904761904761904,
        "1673260717": 0.011904761904761904,
        "315897575": 0.011904761904761904,
        "307068082": 0.011904761904761904,
        "2380835600": 0.011904761904761904,
        "579962917": 0.011904761904761904,
        "61125151": 0.020089285714285712,
        "221803717": 0.011904761904761904,
        "2300445898": 0.011904761904761904,
        "988216526": 0.011904761904761904,
        "162594551": 0.011904761904761904,
        "1431889375": 0.011904761904761904,
        "132687861": 0.011904761904761904,
        "2565616602": 0.011904761904761904,
        "767800": 0.011904761904761904,
        "252860539": 0.013392857142857142,
        "2188545410": 0.011904761904761904,
        "45837736": 0.011904761904761904,
        "132656546": 0.011904761904761904,
        "74954965": 0.011904761904761904,
        "272598655": 0.011904761904761904,
        "2502883539": 0.011904761904761904,
        "544428050": 0.011904761904761904,
        "756158490": 0.011904761904761904,
        "1193125254": 0.011904761904761904,
        "985543027": 0.011904761904761904,
        "2153781255": 0.011904761904761904,
        "1073802067": 0.011904761904761904,
        "237903360": 0.011904761904761904,
        "46888830": 0.011904761904761904,
        "823749043": 0.011904761904761904,
        "2753468812": 0.011904761904761904,
        "25860925": 0.011904761904761904,
        "132306981": 0.011904761904761904,
        "2841791664": 0.011904761904761904,
        "543567716": 0.011904761904761904,
        "1705297002": 0.011904761904761904,
        "1111125584": 0.011904761904761904,
        "55167998": 0.011904761904761904,
        "2365305244": 0.011904761904761904,
        "2775836165": 0.011904761904761904,
        "517883933": 0.011904761904761904,
        "1366541438": 0.011904761904761904,
        "63492240": 0.011904761904761904,
        "277645188": 0.011904761904761904,
        "466786036": 0.011904761904761904,
        "1468968181": 0.011904761904761904,
        "37440873": 0.011904761904761904,
        "48654466": 0.011904761904761904,
        "214842977": 0.011904761904761904,
        "1208186910": 0.011904761904761904,
        "2720128089": 0.011904761904761904,
        "606316616": 0.011904761904761904,
        "145312730": 0.013392857142857142,
        "485675463": 0.011904761904761904,
        "111514588": 0.011904761904761904,
        "351864017": 0.013392857142857142,
        "596151434": 0.011904761904761904,
        "2746249391": 0.011904761904761904,
        "1097615942": 0.011904761904761904,
        "337761893": 0.011904761904761904,
        "1140237624": 0.011904761904761904,
        "2754259598": 0.011904761904761904,
        "130291190": 0.011904761904761904,
        "975505339": 0.011904761904761904,
        "630485446": 0.011904761904761904,
        "282894960": 0.011904761904761904
    }
}