{
    "number_of_nodes": 174.0,
    "number_of_edges": 173.0,
    "cascade_size": 173.0,
    "tree_depth": 3.0,
    "in_degree_distribution": [
        0,
        1,
        1,
        1,
        1,
        1,
        1,
        1,
        1,
        1,
        1,
        1,
        1,
        1,
        1,
        1,
        1,
        1,
        1,
        1,
        1,
        1,
        1,
        1,
        1,
        1,
        1,
        1,
        1,
        1,
        1,
        1,
        1,
        1,
        1,
        1,
        1,
        1,
        1,
        1,
        1,
        1,
        1,
        1,
        1,
        1,
        1,
        1,
        1,
        1,
        1,
        1,
        1,
        1,
        1,
        1,
        1,
        1,
        1,
        1,
        1,
        1,
        1,
        1,
        1,
        1,
        1,
        1,
        1,
        1,
        1,
        1,
        1,
        1,
        1,
        1,
        1,
        1,
        1,
        1,
        1,
        1,
        1,
        1,
        1,
        1,
        1,
        1,
        1,
        1,
        1,
        1,
        1,
        1,
        1,
        1,
        1,
        1,
        1,
        1,
        1,
        1,
        1,
        1,
        1,
        1,
        1,
        1,
        1,
        1,
        1,
        1,
        1,
        1,
        1,
        1,
        1,
        1,
        1,
        1,
        1,
        1,
        1,
        1,
        1,
        1,
        1,
        1,
        1,
        1,
        1,
        1,
        1,
        1,
        1,
        1,
        1,
        1,
        1,
        1,
        1,
        1,
        1,
        1,
        1,
        1,
        1,
        1,
        1,
        1,
        1,
        1,
        1,
        1,
        1,
        1,
        1,
        1,
        1,
        1,
        1,
        1,
        1,
        1,
        1,
        1,
        1,
        1,
        1,
        1,
        1,
        1,
        1,
        1
    ],
    "out_degree_distribution": [
        1,
        167,
        0,
        0,
        0,
        0,
        0,
        0,
        0,
        0,
        0,
        0,
        0,
        0,
        0,
        0,
        0,
        0,
        0,
        0,
        0,
        0,
        0,
        0,
        0,
        0,
        0,
        0,
        0,
        0,
        0,
        0,
        0,
        0,
        0,
        0,
        0,
        0,
        0,
        0,
        0,
        0,
        0,
        0,
        0,
        0,
        0,
        0,
        0,
        0,
        0,
        0,
        0,
        0,
        0,
        0,
        0,
        0,
        0,
        0,
        0,
        0,
        0,
        0,
        0,
        0,
        1,
        0,
        0,
        0,
        0,
        0,
        0,
        0,
        0,
        0,
        3,
        0,
        0,
        0,
        0,
        0,
        0,
        0,
        0,
        0,
        0,
        0,
        0,
        0,
        0,
        0,
        0,
        0,
        0,
        0,
        0,
        0,
        0,
        0,
        0,
        0,
        0,
        0,
        0,
        0,
        0,
        0,
        0,
        0,
        0,
        0,
        0,
        0,
        0,
        0,
        0,
        0,
        0,
        0,
        0,
        0,
        0,
        0,
        0,
        0,
        0,
        0,
        0,
        0,
        1,
        0,
        0,
        0,
        0,
        0,
        0,
        0,
        0,
        0,
        0,
        0,
        0,
        0,
        0,
        0,
        0,
        0,
        0,
        0,
        0,
        0,
        0,
        0,
        0,
        0,
        0,
        0,
        0,
        0,
        0,
        0,
        0,
        0,
        0,
        0,
        0,
        0,
        0,
        0,
        0,
        0,
        0,
        0
    ],
    "propagation_delay_min": 0.0,
    "propagation_delay_mean": 159.08485549132948,
    "propagation_delay_max": 4071.48,
    "reaction_time_min": 0.0,
    "reaction_time_mean": 159.08485549132948,
    "reaction_time_max": 4071.48,
    "betweenness_centrality": {
        "ROOT": 0.0,
        "2467791": 0.005780346820809249,
        "28256946": 0.0,
        "22469584": 0.0,
        "554617385": 0.0,
        "302875042": 0.0,
        "224632012": 0.0,
        "208912348": 0.0,
        "93844875": 0.0,
        "840075498": 0.0,
        "1127543659": 0.0,
        "360033334": 0.0,
        "1901908388": 0.0,
        "944600304": 0.0,
        "1598880560": 0.0,
        "345996945": 0.0,
        "1101212720": 0.0,
        "69767478": 0.0,
        "16709178": 0.0,
        "34746817": 0.0,
        "94333547": 0.0,
        "19843289": 0.0,
        "755829115": 0.0,
        "73978498": 0.0,
        "570840451": 0.0,
        "29207479": 0.0,
        "127988193": 0.0,
        "31487487": 0.0,
        "547055386": 0.0,
        "313591169": 0.0,
        "35348981": 0.0,
        "1191899966": 0.0,
        "1642381": 0.0,
        "22047900": 0.0,
        "552320109": 0.0,
        "304637407": 0.0,
        "17378574": 0.0,
        "21111495": 0.0,
        "1023783762": 0.0,
        "20412603": 0.0,
        "1480464548": 0.0,
        "224236204": 0.0,
        "399725445": 0.0,
        "42719222": 0.0,
        "894473810": 0.0,
        "366571093": 0.0,
        "95297504": 0.0,
        "2238583018": 0.0,
        "1925346193": 0.0,
        "106819122": 0.0,
        "29953896": 0.0,
        "775937803": 0.0,
        "251250051": 0.0,
        "1482939200": 0.0,
        "16617884": 0.0,
        "109084632": 0.0,
        "277443040": 0.0,
        "25141550": 0.0,
        "92739178": 0.0,
        "330694865": 0.0,
        "199379200": 0.0,
        "502234373": 0.0,
        "1935627894": 0.0,
        "15571250": 0.0,
        "246586554": 0.0,
        "64025970": 0.0,
        "215419121": 6.721333512568894e-05,
        "1486117886": 0.0,
        "2181188602": 0.0,
        "1848589849": 0.0,
        "390704970": 0.0,
        "175744670": 0.0,
        "336333450": 0.0,
        "2148179281": 0.0,
        "16316853": 0.0,
        "45515498": 0.0,
        "333743518": 0.00020164000537706682,
        "102794291": 0.0,
        "24237012": 0.0,
        "299095489": 0.0,
        "300528936": 0.0,
        "1848918726": 0.0,
        "55884484": 0.0,
        "1144106352": 0.0,
        "1340408646": 0.0,
        "172679750": 0.0,
        "55301179": 0.0,
        "91064838": 0.0,
        "930683335": 0.0,
        "18959773": 0.0,
        "18782013": 0.0,
        "2245762108": 0.0,
        "422217076": 0.0,
        "176786919": 0.0,
        "230791772": 0.0,
        "2293061179": 0.0,
        "1543219537": 0.0,
        "2250492769": 0.0,
        "2237408230": 0.0,
        "67769538": 0.0,
        "339851912": 0.0,
        "846314766": 0.0,
        "70499035": 0.0,
        "57616018": 0.0,
        "24880242": 0.0,
        "31003230": 0.0,
        "15108561": 0.0,
        "35291255": 0.0,
        "411947317": 0.0,
        "1598555377": 0.0,
        "2279768150": 0.0,
        "385452886": 0.0,
        "103041097": 0.0,
        "487054481": 0.0,
        "24628759": 0.0,
        "134090754": 0.0,
        "136161105": 0.0,
        "318165231": 0.0,
        "338888417": 0.0,
        "42858599": 0.0,
        "26282946": 0.0,
        "948824148": 0.0,
        "167656864": 0.0,
        "586915755": 0.0,
        "2216155062": 0.0,
        "547615079": 0.0,
        "25714576": 0.0,
        "950480676": 0.0,
        "290586992": 0.0,
        "51509963": 0.0,
        "1093222639": 6.721333512568894e-05,
        "18842574": 0.0,
        "65764034": 0.0,
        "1269937770": 0.0,
        "1398198727": 0.0,
        "95486036": 0.0,
        "35589646": 0.0,
        "69741490": 0.0,
        "39905389": 0.0,
        "1518012133": 0.0,
        "475676473": 0.0,
        "66311859": 0.0,
        "392275966": 0.0,
        "828284112": 0.0,
        "33421695": 0.0,
        "176873355": 0.0,
        "64613119": 0.0,
        "602466129": 0.0,
        "931686774": 0.0,
        "308827361": 0.0,
        "796882064": 0.0,
        "1650801541": 0.0,
        "24958111": 0.0,
        "1023445022": 0.0,
        "284369052": 0.0,
        "356892056": 0.0,
        "990627116": 0.0,
        "728180250": 0.0,
        "131519765": 0.0,
        "461263284": 0.0,
        "390696780": 0.0,
        "40703912": 0.0,
        "810053322": 0.0,
        "2206038469": 0.0,
        "481539939": 0.0,
        "1694731742": 0.0,
        "179914856": 0.0,
        "45378764": 0.0,
        "62028707": 0.0,
        "111746087": 0.0,
        "385679461": 0.0,
        "772565977": 0.0,
        "42919671": 0.0,
        "2179657175": 0.0
    },
    "closeness_centrality": {
        "ROOT": 0.0,
        "2467791": 0.005780346820809248,
        "28256946": 0.0077071290944123304,
        "22469584": 0.0077071290944123304,
        "554617385": 0.0077071290944123304,
        "302875042": 0.0077071290944123304,
        "224632012": 0.0077071290944123304,
        "208912348": 0.0077071290944123304,
        "93844875": 0.0077071290944123304,
        "840075498": 0.0077071290944123304,
        "1127543659": 0.0077071290944123304,
        "360033334": 0.0077071290944123304,
        "1901908388": 0.0077071290944123304,
        "944600304": 0.0077071290944123304,
        "1598880560": 0.0077071290944123304,
        "345996945": 0.0077071290944123304,
        "1101212720": 0.0077071290944123304,
        "69767478": 0.0077071290944123304,
        "16709178": 0.0077071290944123304,
        "34746817": 0.0077071290944123304,
        "94333547": 0.0077071290944123304,
        "19843289": 0.0077071290944123304,
        "755829115": 0.0077071290944123304,
        "73978498": 0.0077071290944123304,
        "570840451": 0.0077071290944123304,
        "29207479": 0.0077071290944123304,
        "127988193": 0.0077071290944123304,
        "31487487": 0.0077071290944123304,
        "547055386": 0.0077071290944123304,
        "313591169": 0.0077071290944123304,
        "35348981": 0.0077071290944123304,
        "1191899966": 0.0077071290944123304,
        "1642381": 0.0077071290944123304,
        "22047900": 0.0077071290944123304,
        "552320109": 0.0077071290944123304,
        "304637407": 0.0077071290944123304,
        "17378574": 0.0077071290944123304,
        "21111495": 0.0077071290944123304,
        "1023783762": 0.0077071290944123304,
        "20412603": 0.0077071290944123304,
        "1480464548": 0.0077071290944123304,
        "224236204": 0.0077071290944123304,
        "399725445": 0.0077071290944123304,
        "42719222": 0.0077071290944123304,
        "894473810": 0.0077071290944123304,
        "366571093": 0.0077071290944123304,
        "95297504": 0.0077071290944123304,
        "2238583018": 0.0077071290944123304,
        "1925346193": 0.0077071290944123304,
        "106819122": 0.0077071290944123304,
        "29953896": 0.0077071290944123304,
        "775937803": 0.0077071290944123304,
        "251250051": 0.0077071290944123304,
        "1482939200": 0.0077071290944123304,
        "16617884": 0.0077071290944123304,
        "109084632": 0.0077071290944123304,
        "277443040": 0.0077071290944123304,
        "25141550": 0.0077071290944123304,
        "92739178": 0.0077071290944123304,
        "330694865": 0.0077071290944123304,
        "199379200": 0.0077071290944123304,
        "502234373": 0.0077071290944123304,
        "1935627894": 0.0077071290944123304,
        "15571250": 0.0077071290944123304,
        "246586554": 0.0077071290944123304,
        "64025970": 0.0077071290944123304,
        "215419121": 0.0077071290944123304,
        "1486117886": 0.0077071290944123304,
        "2181188602": 0.0077071290944123304,
        "1848589849": 0.0077071290944123304,
        "390704970": 0.0077071290944123304,
        "175744670": 0.0077071290944123304,
        "336333450": 0.0077071290944123304,
        "2148179281": 0.0077071290944123304,
        "16316853": 0.0077071290944123304,
        "45515498": 0.0077071290944123304,
        "333743518": 0.0077071290944123304,
        "102794291": 0.0077071290944123304,
        "24237012": 0.0077071290944123304,
        "299095489": 0.0077071290944123304,
        "300528936": 0.0077071290944123304,
        "1848918726": 0.0077071290944123304,
        "55884484": 0.008670520231213872,
        "1144106352": 0.0077071290944123304,
        "1340408646": 0.0077071290944123304,
        "172679750": 0.0077071290944123304,
        "55301179": 0.0077071290944123304,
        "91064838": 0.0077071290944123304,
        "930683335": 0.0077071290944123304,
        "18959773": 0.0077071290944123304,
        "18782013": 0.0077071290944123304,
        "2245762108": 0.0077071290944123304,
        "422217076": 0.0077071290944123304,
        "176786919": 0.0077071290944123304,
        "230791772": 0.008670520231213872,
        "2293061179": 0.0077071290944123304,
        "1543219537": 0.0077071290944123304,
        "2250492769": 0.0077071290944123304,
        "2237408230": 0.0077071290944123304,
        "67769538": 0.0077071290944123304,
        "339851912": 0.0077071290944123304,
        "846314766": 0.0077071290944123304,
        "70499035": 0.0077071290944123304,
        "57616018": 0.0077071290944123304,
        "24880242": 0.0077071290944123304,
        "31003230": 0.0077071290944123304,
        "15108561": 0.0077071290944123304,
        "35291255": 0.008670520231213872,
        "411947317": 0.0077071290944123304,
        "1598555377": 0.0077071290944123304,
        "2279768150": 0.0077071290944123304,
        "385452886": 0.0077071290944123304,
        "103041097": 0.0077071290944123304,
        "487054481": 0.0077071290944123304,
        "24628759": 0.0077071290944123304,
        "134090754": 0.0077071290944123304,
        "136161105": 0.0077071290944123304,
        "318165231": 0.0077071290944123304,
        "338888417": 0.0077071290944123304,
        "42858599": 0.0077071290944123304,
        "26282946": 0.0077071290944123304,
        "948824148": 0.008670520231213872,
        "167656864": 0.0077071290944123304,
        "586915755": 0.0077071290944123304,
        "2216155062": 0.0077071290944123304,
        "547615079": 0.0077071290944123304,
        "25714576": 0.0077071290944123304,
        "950480676": 0.0077071290944123304,
        "290586992": 0.0077071290944123304,
        "51509963": 0.0077071290944123304,
        "1093222639": 0.0077071290944123304,
        "18842574": 0.0077071290944123304,
        "65764034": 0.0077071290944123304,
        "1269937770": 0.0077071290944123304,
        "1398198727": 0.0077071290944123304,
        "95486036": 0.0077071290944123304,
        "35589646": 0.0077071290944123304,
        "69741490": 0.0077071290944123304,
        "39905389": 0.0077071290944123304,
        "1518012133": 0.0077071290944123304,
        "475676473": 0.0077071290944123304,
        "66311859": 0.0077071290944123304,
        "392275966": 0.0077071290944123304,
        "828284112": 0.0077071290944123304,
        "33421695": 0.0077071290944123304,
        "176873355": 0.0077071290944123304,
        "64613119": 0.0077071290944123304,
        "602466129": 0.0077071290944123304,
        "931686774": 0.0077071290944123304,
        "308827361": 0.008670520231213872,
        "796882064": 0.0077071290944123304,
        "1650801541": 0.0077071290944123304,
        "24958111": 0.0077071290944123304,
        "1023445022": 0.0077071290944123304,
        "284369052": 0.0077071290944123304,
        "356892056": 0.0077071290944123304,
        "990627116": 0.0077071290944123304,
        "728180250": 0.0077071290944123304,
        "131519765": 0.0077071290944123304,
        "461263284": 0.0077071290944123304,
        "390696780": 0.0077071290944123304,
        "40703912": 0.0077071290944123304,
        "810053322": 0.0077071290944123304,
        "2206038469": 0.0077071290944123304,
        "481539939": 0.0077071290944123304,
        "1694731742": 0.0077071290944123304,
        "179914856": 0.0077071290944123304,
        "45378764": 0.0077071290944123304,
        "62028707": 0.0077071290944123304,
        "111746087": 0.0077071290944123304,
        "385679461": 0.0077071290944123304,
        "772565977": 0.0077071290944123304,
        "42919671": 0.0077071290944123304,
        "2179657175": 0.0077071290944123304
    }
}